slice_to_py_dist/__init__.py
slice_to_py_dist/__main__.py
slice_to_py_dist/build_sdist.py
slice_to_py_dist/custom_build_backend/backend.py
slice_to_py_dist/types.py
slice_to_py_dist/utils.py
slice_to_py_dist-0.3.1.dist-info/METADATA
slice_to_py_dist-0.3.1.dist-info/WHEEL
slice_to_py_dist-0.3.1.dist-info/RECORD
