Metadata-Version: 2.1
Name: slice-to-py-dist
Version: 0.3.1
Summary: Pack a set of ZeroC/ICE slice files (.ice) into python distribution package.
Home-page: https://gitlab.com/evgk/slice_to_py_dist
Author: Evgeny Klunko
Author-email: eklunko@gmail.com
Requires-Python: >=3.8,<4.0
Classifier: Programming Language :: Python :: 3
Classifier: Programming Language :: Python :: 3.8
Classifier: Programming Language :: Python :: 3.9
Classifier: Programming Language :: Python :: 3.10
Classifier: Programming Language :: Python :: 3.11
Requires-Dist: build (>=0.10.0,<0.11.0)
Requires-Dist: configargparse (>=1.5.5,<2.0.0)
Requires-Dist: toml (>=0.10.2,<0.11.0)
Project-URL: Repository, https://gitlab.com/evgk/slice_to_py_dist
